sec_api_utils/__init__.py
sec_api_utils/data_analytics/FairValueCalculator.py
sec_api_utils/data_analytics/MonteCarloSampling.py
sec_api_utils/data_analytics/__init__.py
sec_api_utils/data_loading/CompanyTickerHandler.py
sec_api_utils/data_loading/SECAPILoader.py
sec_api_utils/data_loading/SECFileDataLoader.py
sec_api_utils/data_loading/__init__.py
sec_api_utils/data_representation/SECBaseMeasure.py
sec_api_utils/data_representation/SECCompanyInfo.py
sec_api_utils/data_representation/SECFilingInfo.py
sec_api_utils/data_representation/SECUnits.py
sec_api_utils/data_representation/__init__.py
sec_api_utils/general/Constants.py
sec_api_utils/general/SECConstants.py
sec_api_utils/general/__init__.py
sec_api_utils/plotting/SECUnitPlotter.py
sec_api_utils/plotting/__init__.py
sec_api_utils-0.2.0.dist-info/METADATA
sec_api_utils-0.2.0.dist-info/WHEEL
sec_api_utils-0.2.0.dist-info/licenses/LICENSE
sec_api_utils-0.2.0.dist-info/RECORD
