Metadata-Version: 2.1
Name: sec_api_utils
Version: 0.2.0
Summary: A non-official wrapper for the sec-edgar-api, with built-in representation classes.
Project-URL: Homepage, https://github.com/bruprod/sec_api_utils
Project-URL: Bug Tracker, https://github.com/bruprod/sec_api_utils/issues
Author-email: Andreas Bruchmann <ba@abruchmann.at>
License-File: LICENSE
Classifier: License :: OSI Approved :: MIT License
Classifier: Operating System :: OS Independent
Classifier: Programming Language :: Python :: 3
Requires-Python: >=3.7
